{
    "cpu": "General",
    "groups": [
        {
            "group": {
                "name": "General regs",
                "description": "General register generated by SPSDK"
            },
            "registers": [
                {
                    "id": "field000",
                    "offset_int": "0x0",
                    "reg_width": "32",
                    "name": "ConfigOption0",
                    "description": "SEMC NAND Configuration Option 0",
                    "reset_value_int": "0xd0000100",
                    "bitfields": [
                        {
                            "id": "field000-bits0-2",
                            "offset": "0x0",
                            "width": "3",
                            "name": "OnfiVersion",
                            "access": "R/W",
                            "reset_value_int": "0x0",
                            "description": "ONFI version"
                        },
                        {
                            "id": "field000-bit3",
                            "offset": "0x3",
                            "width": "1",
                            "name": "EdoMode",
                            "access": "R/W",
                            "reset_value_int": "0x0",
                            "description": "EDO mode",
                            "values": [
                                {
                                    "name": "Disabled",
                                    "value": 0,
                                    "description": "EDO mode disabled"
                                },
                                {
                                    "name": "Enabled",
                                    "value": 1,
                                    "description": "EDO mode enabled"
                                }
                            ]
                        },
                        {
                            "id": "field000-bits4-6",
                            "offset": "0x4",
                            "width": "3",
                            "name": "OnfiTimingMode",
                            "access": "R/W",
                            "reset_value_int": "0x0",
                            "description": "ONFI Timing mode",
                            "values": [
                                {
                                    "name": "10MHz",
                                    "value": 0,
                                    "description": "Mode 0, 10MHz"
                                },
                                {
                                    "name": "20MHz",
                                    "value": 1,
                                    "description": "Mode 1, 20MHz"
                                },
                                {
                                    "name": "28MHz",
                                    "value": 2,
                                    "description": "Mode 2, 28MHz"
                                },
                                {
                                    "name": "33MHz",
                                    "value": 3,
                                    "description": "Mode 3, 33MHz"
                                },
                                {
                                    "name": "40MHz",
                                    "value": 4,
                                    "description": "Mode 4, 40MHz"
                                },
                                {
                                    "name": "50MHz",
                                    "value": 5,
                                    "description": "Mode 5, 50MHz"
                                },
                                {
                                    "name": "Fastest0",
                                    "value": 6,
                                    "description": "Mode 6, Fastest mode 0"
                                },
                                {
                                    "name": "Fastest1",
                                    "value": 7,
                                    "description": "Mode 7, Fastest mode 1"
                                }
                            ]
                        },
                        {
                            "id": "field000-bit7",
                            "offset": "0x7",
                            "width": "1",
                            "access": "R/W",
                            "reset_value_int": "0x0",
                            "description": "Reserved for future use"
                        },
                        {
                            "id": "field000-bits8-9",
                            "offset": "0x8",
                            "width": "2",
                            "name": "IoPortDiv8",
                            "access": "R/W",
                            "reset_value_int": "0x1",
                            "description": "IO port size, Minimum is 1"
                        },
                        {
                            "id": "field000-bits10-11",
                            "offset": "0xa",
                            "width": "2",
                            "access": "R/W",
                            "reset_value_int": "0x0",
                            "description": "Reserved for future use"
                        },
                        {
                            "id": "field000-bits12-14",
                            "offset": "0xc",
                            "width": "3",
                            "name": "PcsSelection",
                            "access": "R/W",
                            "reset_value_int": "0x0",
                            "description": "SEMC NAND PCS selection",
                            "values": [
                                {
                                    "name": "CSX0",
                                    "value": 0,
                                    "description": "SEMC NAND CSX0"
                                },
                                {
                                    "name": "CSX1",
                                    "value": 1,
                                    "description": "SEMC NAND CSX1"
                                },
                                {
                                    "name": "CSX2",
                                    "value": 2,
                                    "description": "SEMC NAND CSX2"
                                },
                                {
                                    "name": "CSX3",
                                    "value": 3,
                                    "description": "SEMC NAND CSX3"
                                },
                                {
                                    "name": "A8",
                                    "value": 4,
                                    "description": "SEMC NAND A8"
                                }
                            ]
                        },
                        {
                            "id": "field000-bit15",
                            "offset": "0xf",
                            "width": "1",
                            "access": "R/W",
                            "reset_value_int": "0x0",
                            "description": "Reserved for future use"
                        },
                        {
                            "id": "field000-bit16",
                            "offset": "0x10",
                            "width": "1",
                            "name": "EccType",
                            "access": "R/W",
                            "reset_value_int": "0x0",
                            "description": "ECC type",
                            "values": [
                                {
                                    "name": "SW",
                                    "value": 0,
                                    "description": "Software ECC"
                                },
                                {
                                    "name": "HW",
                                    "value": 1,
                                    "description": "Hardware ECC"
                                }
                            ]
                        },
                        {
                            "id": "field000-bit17",
                            "offset": "0x11",
                            "width": "1",
                            "name": "EccStatus",
                            "access": "R/W",
                            "reset_value_int": "0x0",
                            "description": "ECC status",
                            "values": [
                                {
                                    "name": "Enabled",
                                    "value": 0,
                                    "description": "ECC enabled"
                                },
                                {
                                    "name": "Disabled",
                                    "value": 1,
                                    "description": "ECC disabled"
                                }
                            ]
                        },
                        {
                            "id": "field000-bits18-23",
                            "offset": "0x12",
                            "width": "6",
                            "access": "R/W",
                            "reset_value_int": "0x0",
                            "description": "Reserved for future use"
                        },
                        {
                            "id": "field000-bits24-27",
                            "offset": "0x18",
                            "width": "4",
                            "access": "R/W",
                            "reset_value_int": "0x0",
                            "description": "Reserved for future use"
                        },
                        {
                            "id": "field000-bits28-31",
                            "offset": "0x1c",
                            "width": "4",
                            "access": "R/W",
                            "reset_value_int": "0xd",
                            "description": "Tag, fixed value 0xD"
                        }
                    ]
                }
            ]
        }
    ]
}